README.txt
setup.py
Products/__init__.py
Products.PolicyHTTPCacheManager.egg-info/PKG-INFO
Products.PolicyHTTPCacheManager.egg-info/SOURCES.txt
Products.PolicyHTTPCacheManager.egg-info/dependency_links.txt
Products.PolicyHTTPCacheManager.egg-info/entry_points.txt
Products.PolicyHTTPCacheManager.egg-info/namespace_packages.txt
Products.PolicyHTTPCacheManager.egg-info/not-zip-safe
Products.PolicyHTTPCacheManager.egg-info/requires.txt
Products.PolicyHTTPCacheManager.egg-info/top_level.txt
Products/PolicyHTTPCacheManager/PolicyHTTPCacheManager.py
Products/PolicyHTTPCacheManager/__init__.py
Products/PolicyHTTPCacheManager/cache.gif
Products/PolicyHTTPCacheManager/cmf_compat.py
Products/PolicyHTTPCacheManager/makefile.in
Products/PolicyHTTPCacheManager/version.txt
Products/PolicyHTTPCacheManager/dtml/addPolicy.dtml
Products/PolicyHTTPCacheManager/dtml/propsPolicy.dtml
Products/PolicyHTTPCacheManager/dtml/statsPolicy.dtml
Products/PolicyHTTPCacheManager/tests/__init__.py
Products/PolicyHTTPCacheManager/tests/cache_manager.txt
Products/PolicyHTTPCacheManager/tests/framework.py
Products/PolicyHTTPCacheManager/tests/test_doctests.py
docs/CREDITS.txt
docs/HISTORY.txt
docs/INSTALL.txt
docs/LICENSE.txt
