Metadata-Version: 1.0
Name: Products.PolicyHTTPCacheManager
Version: 1.2
Summary: Cache manager which delegates policy to CMF's caching policy manager
Home-page: http://svn.plone.org/svn/collective/Products.PolicyHTTPCacheManager
Author: Sidnei da Silva
Author-email: plone-developers@lists.sourceforge.net
License: ZPL
Platform: UNKNOWN
Classifier: Framework :: Plone
Classifier: Programming Language :: Python
Classifier: Topic :: Software Development :: Libraries :: Python Modules
